ZookeeperManager.py
robotframework_zookeepermanager-2.0.2.dist-info/LICENSE
robotframework_zookeepermanager-2.0.2.dist-info/METADATA
robotframework_zookeepermanager-2.0.2.dist-info/WHEEL
robotframework_zookeepermanager-2.0.2.dist-info/top_level.txt
robotframework_zookeepermanager-2.0.2.dist-info/RECORD
